qdrant_client/__init__.py
qdrant_client/_pydantic_compat.py
qdrant_client/async_client_base.py
qdrant_client/async_qdrant_client.py
qdrant_client/async_qdrant_fastembed.py
qdrant_client/async_qdrant_remote.py
qdrant_client/auth/__init__.py
qdrant_client/auth/bearer_auth.py
qdrant_client/client_base.py
qdrant_client/common/__init__.py
qdrant_client/common/client_exceptions.py
qdrant_client/common/client_warnings.py
qdrant_client/common/version_check.py
qdrant_client/connection.py
qdrant_client/conversions/__init__.py
qdrant_client/conversions/common_types.py
qdrant_client/conversions/conversion.py
qdrant_client/embed/_inspection_cache.py
qdrant_client/embed/common.py
qdrant_client/embed/embed_inspector.py
qdrant_client/embed/embedder.py
qdrant_client/embed/model_embedder.py
qdrant_client/embed/models.py
qdrant_client/embed/schema_parser.py
qdrant_client/embed/type_inspector.py
qdrant_client/embed/utils.py
qdrant_client/fastembed_common.py
qdrant_client/grpc/__init__.py
qdrant_client/grpc/collections_pb2.py
qdrant_client/grpc/collections_pb2_grpc.py
qdrant_client/grpc/collections_service_pb2.py
qdrant_client/grpc/collections_service_pb2_grpc.py
qdrant_client/grpc/json_with_int_pb2.py
qdrant_client/grpc/json_with_int_pb2_grpc.py
qdrant_client/grpc/points_pb2.py
qdrant_client/grpc/points_pb2_grpc.py
qdrant_client/grpc/points_service_pb2.py
qdrant_client/grpc/points_service_pb2_grpc.py
qdrant_client/grpc/qdrant_pb2.py
qdrant_client/grpc/qdrant_pb2_grpc.py
qdrant_client/grpc/snapshots_service_pb2.py
qdrant_client/grpc/snapshots_service_pb2_grpc.py
qdrant_client/http/__init__.py
qdrant_client/http/api/__init__.py
qdrant_client/http/api/aliases_api.py
qdrant_client/http/api/beta_api.py
qdrant_client/http/api/collections_api.py
qdrant_client/http/api/distributed_api.py
qdrant_client/http/api/indexes_api.py
qdrant_client/http/api/points_api.py
qdrant_client/http/api/search_api.py
qdrant_client/http/api/service_api.py
qdrant_client/http/api/snapshots_api.py
qdrant_client-1.14.0.dist-info/LICENSE
qdrant_client-1.14.0.dist-info/METADATA
qdrant_client-1.14.0.dist-info/WHEEL
qdrant_client-1.14.0.dist-info/RECORD
