Metadata-Version: 2.3
Name: qdrant-client
Version: 1.14.0
Summary: Client library for the Qdrant vector search engine
License: Apache-2.0
Keywords: vector,search,neural,matching,client
Author: Andrey Vasnetsov
Author-email: andrey@qdrant.tech
Requires-Python: >=3.9
Classifier: License :: OSI Approved :: Apache Software License
Classifier: Programming Language :: Python :: 3
Classifier: Programming Language :: Python :: 3.9
Classifier: Programming Language :: Python :: 3.10
Classifier: Programming Language :: Python :: 3.11
Classifier: Programming Language :: Python :: 3.12
Classifier: Programming Language :: Python :: 3.13
Provides-Extra: fastembed
Provides-Extra: fastembed-gpu
Requires-Dist: fastembed (==0.6.1) ; extra == "fastembed"
Requires-Dist: fastembed-gpu (==0.6.1) ; extra == "fastembed-gpu"
Requires-Dist: grpcio (>=1.41.0)
Requires-Dist: httpx[http2] (>=0.20.0)
Requires-Dist: numpy (>=1.21) ; python_version >= "3.10" and python_version < "3.12"
Requires-Dist: numpy (>=1.21,<2.1.0) ; python_version < "3.10"
Requires-Dist: numpy (>=1.26) ; python_version == "3.12"
Requires-Dist: numpy (>=2.1.0) ; python_version >= "3.13"
Requires-Dist: portalocker (>=2.7.0,<3.0.0)
Requires-Dist: protobuf (>=3.20.0)
Requires-Dist: pydantic (>=1.10.8,!=2.0.*,!=2.1.*,!=2.2.0)
Requires-Dist: urllib3 (>=1.26.14,<3)
Project-URL: Homepage, https://github.com/qdrant/qdrant-client
Project-URL: Repository, https://github.com/qdrant/qdrant-client
